{
  "project_info": {
    "project_number": "357972744272",
    "project_id": "letmegoo-2aab1",
    "storage_bucket": "letmegoo-2aab1.firebasestorage.app"
  },
  "client": [
    {
      "client_info": {
        "mobilesdk_app_id": "1:357972744272:android:586f14a3a8d2e93ee19955",
        "android_client_info": {
          "package_name": "com.example.letmegoo"
        }
      },
      "oauth_client": [
        {
          "client_id": "357972744272-ruir0d8euj6764v7e3ej17t5tponffjb.apps.googleusercontent.com",
          "client_type": 1,
          "android_info": {
            "package_name": "com.example.letmegoo",
            "certificate_hash": "e88c2a2306dd8e1a2a2d3b3935049df4aed29459"
          }
        },
        {
          "client_id": "357972744272-hkf4e8kias78kmr85cok76uom5t8of4g.apps.googleusercontent.com",
          "client_type": 3
        }
      ],
      "api_key": [
        {
          "current_key": "AIzaSyCcglrv82GSKICJ7efUsy4tVPTbq2wN0UY"
        }
      ],
      "services": {
        "appinvite_service": {
          "other_platform_oauth_client": [
            {
              "client_id": "357972744272-hkf4e8kias78kmr85cok76uom5t8of4g.apps.googleusercontent.com",
              "client_type": 3
            },
            {
              "client_id": "357972744272-kd6kb06pl69huaroo0t593nae0eh35e9.apps.googleusercontent.com",
              "client_type": 2,
              "ios_info": {
                "bundle_id": "com.example.letmegoo"
              }
            }
          ]
        }
      }
    }
  ],
  "configuration_version": "1"
}